{
    "scaling": {
        "crs": [1,3,5,7,9,11],
        "primary_cr": 3,
        "trait": {
            "Focused Hunter": [
                {
                    "crs": [1, 3, 5, 7, 9, 11],
                    "entries": [
                        "Being {@condition Prone|XPHB} does not impose disadvantage on the <name>'s ranged weapon attacks."
                    ]
                }
            ]
        },
        "action": {
            "Multiattack": [
                {
                    "crs": [1, 3, 5, 7, 9, 11],
                    "entries": [
                        "The <name> makes two weapon attacks."
                    ]
                }
            ],
            "Ranged Weapon": [
                {
                    "crs": [1, 3, 5, 7, 9, 11],
                    "entries": [
                        "{@atkr rw} <hit_default>, range 150/300 ft., one target <dmg_strong> bludgeoning or piercing damage."
                    ]
                }
            ],
            "Sidearm": [
                {
                    "crs": [1, 3, 5, 7, 9, 11],
                    "entries": [
                        "{@atkr mw} <hit_default>, reach 5 ft., one_target <dmg_puny> piercing damage."
                    ]
                }
            ],
            "Overwatch": [
                {
                    "crs": [1, 3, 5, 7, 9, 11],
                    "entries": [
                        "The <name> choses a 20-foot cube centred on a point it can see within 120 feet. Each time a creature enters the area for the first time on a turn or starts its turn there, the <name> can take a Ranged Weapon attack against the creature. The attack does not require a reaction, however, the <name> must be able to see the creature and must not be {@condition Incapacitated|XPHB}.",
                        "The effects last until the start of the <name>'s next turn and end early once it makes three attacks in this way."
                    ]
                }
            ]
        },
        "bonus": {
            "Steady Aim": [
                {
                    "crs": [1, 3, 5, 7, 9, 11],
                    "entries": [
                        "If the <name> has not moved on the current turn it can gain {@variantrule Advantage|XPHB} on the next ranged weapon attack roll it makes before the start of its next turn. On a hit, the attack deals an additional 6 ({@dice 1d10}) damage.",
                        "When it uses this bonus action, the <name>'s speed is reduced to 0 until the start of its next turn."
                    ]
                }
            ]
        },
        "reaction": {}
    },
    "base_statblock": {
        "name": "Sniper",
        "source": "J:Warriors",
        "size": ["S", "M"],
        "type": {
            "type": "humanoid",
            "tags": [
                "warrior",
                "artillery"
            ]
        },
        "alignment": [
            "A"
        ],
        "ac": "ac_light",
        "hp": "hp_weak",
        "speed": {
            "walk": 30
        },
        "str": 14,
        "dex": 16,
        "con": 12,
        "int": 8,
        "wis": 12,
        "cha": 10,
        "save": {
            "dex": "+3+PB"
        },
        "skill": {
            "perception": "+6",
            "stealth": "+6"
        },
        "passive": "11",
        "cr": "-",
        "languages": [
            "any three languages (typically including common)"
        ],
        "trait": [],
        "action": [],
        "bonus": [],
        "reaction": [],
        "damageTags": [
            "P"
        ],
        "miscTags": [
            "MW",
            "RW"
        ]
    }
}